boule/__init__.py
boule/_ellipsoid.py
boule/_realizations.py
boule/_sphere.py
boule/_triaxialellipsoid.py
boule/_version.py
boule/_version_generated.py
boule/tests/__init__.py
boule/tests/test_ellipsoid.py
boule/tests/test_pymap3d.py
boule/tests/test_sphere.py
boule/tests/test_triaxialellipsoid.py
boule/tests/utils.py
boule-0.4.1.dist-info/LICENSE.txt
boule-0.4.1.dist-info/METADATA
boule-0.4.1.dist-info/WHEEL
boule-0.4.1.dist-info/top_level.txt
boule-0.4.1.dist-info/zip-safe
boule-0.4.1.dist-info/RECORD
