Metadata-Version: 2.1
Name: boule
Version: 0.4.1
Summary: Reference ellipsoids for geodesy and geophysics
Home-page: https://github.com/fatiando/boule
Author: The Boule Developers
Author-email: fatiandoaterra@protonmail.com
Maintainer: Leonardo Uieda
Maintainer-email: leouieda@gmail.com
License: BSD 3-Clause License
Project-URL: Documentation, https://www.fatiando.org/boule
Project-URL: Release Notes, https://github.com/fatiando/boule/releases
Project-URL: Bug Tracker, https://github.com/fatiando/boule/issues
Project-URL: Source Code, https://github.com/fatiando/boule
Keywords: geophysics,geodesy,data
Platform: any
Classifier: Development Status :: 3 - Alpha
Classifier: Intended Audience :: Science/Research
Classifier: Intended Audience :: Developers
Classifier: Intended Audience :: Education
Classifier: License :: OSI Approved :: BSD License
Classifier: Natural Language :: English
Classifier: Operating System :: OS Independent
Classifier: Topic :: Scientific/Engineering
Classifier: Topic :: Software Development :: Libraries
Classifier: Programming Language :: Python :: 3 :: Only
Classifier: Programming Language :: Python :: 3.7
Classifier: Programming Language :: Python :: 3.8
Classifier: Programming Language :: Python :: 3.9
Classifier: Programming Language :: Python :: 3.10
Requires-Python: >=3.7
License-File: LICENSE.txt
Requires-Dist: numpy (>=1.19)
Requires-Dist: attrs (>=19.3.0)
